py_niconico_comment/__init__.py
py_niconico_comment/niconico.py
py_niconico_comment/skeleton.py
py_niconico_comment/utils.py
py_niconico_comment-0.0.3.dist-info/AUTHORS.rst
py_niconico_comment-0.0.3.dist-info/LICENSE.txt
py_niconico_comment-0.0.3.dist-info/METADATA
py_niconico_comment-0.0.3.dist-info/WHEEL
py_niconico_comment-0.0.3.dist-info/entry_points.txt
py_niconico_comment-0.0.3.dist-info/top_level.txt
py_niconico_comment-0.0.3.dist-info/RECORD
