Metadata-Version: 2.1
Name: py-niconico-comment
Version: 0.0.3
Summary: niconico comment utils
Home-page: https://github.com/nicovideo-comment/py-niconico-comment
Author: poipoii
Author-email: earth.sama@gmail.com
License: mit
Project-URL: Documentation, https://py-niconico-comment.readthedocs.io/en/latest/
Platform: any
Classifier: Development Status :: 4 - Beta
Classifier: Programming Language :: Python
Classifier: Programming Language :: Python :: 3.6
Requires-Python: >= 3.6
Requires-Dist: cssselect (==1.1.0)
Requires-Dist: lxml (==4.4.2)
Requires-Dist: requests (==2.22.0)
Provides-Extra: testing
Requires-Dist: pytest ; extra == 'testing'
Requires-Dist: pytest-cov ; extra == 'testing'
